hammal.py
hammal-0.1.3.dist-info/METADATA
hammal-0.1.3.dist-info/WHEEL
hammal-0.1.3.dist-info/top_level.txt
hammal-0.1.3.dist-info/RECORD
